django_ewiz/__init__.py
django_ewiz/attacher.py
django_ewiz/base.py
django_ewiz/compiler.py
django_ewiz/decompiler.py
django_ewiz/urlbuilders.py
django_ewiz-1.5.4.dist-info/DESCRIPTION.rst
django_ewiz-1.5.4.dist-info/METADATA
django_ewiz-1.5.4.dist-info/RECORD
django_ewiz-1.5.4.dist-info/WHEEL
django_ewiz-1.5.4.dist-info/metadata.json
django_ewiz-1.5.4.dist-info/top_level.txt
