Metadata-Version: 2.0
Name: django-ewiz
Version: 1.5.4
Summary: A non-relational Django database backend that utilizes EnterpriseWizard's REST interface.
Home-page: https://github.com/kavdev/django-ewiz
Author: Alex Kavanaugh
Author-email: kavanaugh.development@outlook.com
License: GNU LGPL (http://www.gnu.org/licenses/lgpl.html)
Keywords: django ewiz enterprise wizard srs
Platform: UNKNOWN
Classifier: Development Status :: 5 - Production/Stable
Classifier: Environment :: Web Environment
Classifier: Framework :: Django
Classifier: Intended Audience :: Developers
Classifier: License :: OSI Approved :: GNU Library or Lesser General Public License (LGPL)
Classifier: Natural Language :: English
Classifier: Operating System :: OS Independent
Classifier: Programming Language :: Python :: 3.4
Classifier: Topic :: Software Development :: Libraries :: Python Modules
Classifier: Topic :: Database :: Database Engines/Servers
Classifier: Topic :: Utilities
Requires-Dist: Django (>=1.5)
Requires-Dist: djangotoolbox (>=1.6.2)
Requires-Dist: requests (>=2.3.0)
